jmq_olt_huawei/__init__.py
jmq_olt_huawei/ma56xxt.py
jmq_olt_huawei-1.0.0.dist-info/licenses/LICENSE
jmq_olt_huawei-1.0.0.dist-info/METADATA
jmq_olt_huawei-1.0.0.dist-info/WHEEL
jmq_olt_huawei-1.0.0.dist-info/top_level.txt
jmq_olt_huawei-1.0.0.dist-info/RECORD
